{"nodes": [{"id": "c_users_carle_desktop_sogna_sogna_curator_engines_sentinel_apps_worker_src_index_ts", "label": "index.ts", "file_type": "code", "source_file": "C:\\Users\\carle\\Desktop\\Sogna\\Sogna\\Curator\\engines\\Sentinel\\apps\\worker\\src\\index.ts", "source_location": "L1", "confidence_score": 1.0}, {"id": "index_bootstrapsentinel", "label": "bootstrapSentinel()", "file_type": "code", "source_file": "C:\\Users\\carle\\Desktop\\Sogna\\Sogna\\Curator\\engines\\Sentinel\\apps\\worker\\src\\index.ts", "source_location": "L11", "confidence_score": 1.0}], "edges": [{"source": "c_users_carle_desktop_sogna_sogna_curator_engines_sentinel_apps_worker_src_index_ts", "target": "worker", "relation": "imports", "confidence": "EXTRACTED", "confidence_score": 1.0, "audit_reason": null, "source_file": "C:\\Users\\carle\\Desktop\\Sogna\\Sogna\\Curator\\engines\\Sentinel\\apps\\worker\\src\\index.ts", "source_location": "L8", "weight": 1.0}, {"source": "c_users_carle_desktop_sogna_sogna_curator_engines_sentinel_apps_worker_src_index_ts", "target": "c_users_carle_desktop_sogna_sogna_curator_engines_sentinel_apps_worker_src_activities", "relation": "imports", "confidence": "EXTRACTED", "confidence_score": 1.0, "audit_reason": null, "source_file": "C:\\Users\\carle\\Desktop\\Sogna\\Sogna\\Curator\\engines\\Sentinel\\apps\\worker\\src\\index.ts", "source_location": "L9", "weight": 1.0}, {"source": "c_users_carle_desktop_sogna_sogna_curator_engines_sentinel_apps_worker_src_index_ts", "target": "index_bootstrapsentinel", "relation": "contains", "confidence": "EXTRACTED", "confidence_score": 1.0, "audit_reason": null, "source_file": "C:\\Users\\carle\\Desktop\\Sogna\\Sogna\\Curator\\engines\\Sentinel\\apps\\worker\\src\\index.ts", "source_location": "L11", "weight": 1.0}], "raw_calls": [{"caller_nid": "index_bootstrapsentinel", "callee": "log", "source_file": "C:\\Users\\carle\\Desktop\\Sogna\\Sogna\\Curator\\engines\\Sentinel\\apps\\worker\\src\\index.ts", "source_location": "L12"}, {"caller_nid": "index_bootstrapsentinel", "callee": "create", "source_file": "C:\\Users\\carle\\Desktop\\Sogna\\Sogna\\Curator\\engines\\Sentinel\\apps\\worker\\src\\index.ts", "source_location": "L15"}, {"caller_nid": "index_bootstrapsentinel", "callee": "resolve", "source_file": "C:\\Users\\carle\\Desktop\\Sogna\\Sogna\\Curator\\engines\\Sentinel\\apps\\worker\\src\\index.ts", "source_location": "L16"}, {"caller_nid": "index_bootstrapsentinel", "callee": "log", "source_file": "C:\\Users\\carle\\Desktop\\Sogna\\Sogna\\Curator\\engines\\Sentinel\\apps\\worker\\src\\index.ts", "source_location": "L21"}, {"caller_nid": "index_bootstrapsentinel", "callee": "run", "source_file": "C:\\Users\\carle\\Desktop\\Sogna\\Sogna\\Curator\\engines\\Sentinel\\apps\\worker\\src\\index.ts", "source_location": "L22"}]}