{"nodes": [{"id": "c_users_carle_desktop_sogna_sogna_sognatore_src_sentinel_sognatore_policytypes_ts", "label": "PolicyTypes.ts", "file_type": "code", "source_file": "C:\\Users\\carle\\Desktop\\Sogna\\Sogna\\Sognatore\\src\\Sentinel-Sognatore\\PolicyTypes.ts", "source_location": "L1", "confidence_score": 1.0}, {"id": "policytypes_evaluaterule", "label": "evaluateRule()", "file_type": "code", "source_file": "C:\\Users\\carle\\Desktop\\Sogna\\Sogna\\Sognatore\\src\\Sentinel-Sognatore\\PolicyTypes.ts", "source_location": "L71", "confidence_score": 1.0}, {"id": "policytypes_scancontent", "label": "scanContent()", "file_type": "code", "source_file": "C:\\Users\\carle\\Desktop\\Sogna\\Sogna\\Sognatore\\src\\Sentinel-Sognatore\\PolicyTypes.ts", "source_location": "L84", "confidence_score": 1.0}, {"id": "policytypes_validatepreexecution", "label": "validatePreExecution()", "file_type": "code", "source_file": "C:\\Users\\carle\\Desktop\\Sogna\\Sogna\\Sognatore\\src\\Sentinel-Sognatore\\PolicyTypes.ts", "source_location": "L110", "confidence_score": 1.0}, {"id": "policytypes_validatepredeployment", "label": "validatePreDeployment()", "file_type": "code", "source_file": "C:\\Users\\carle\\Desktop\\Sogna\\Sogna\\Sognatore\\src\\Sentinel-Sognatore\\PolicyTypes.ts", "source_location": "L116", "confidence_score": 1.0}, {"id": "policytypes_validateresource", "label": "validateResource()", "file_type": "code", "source_file": "C:\\Users\\carle\\Desktop\\Sogna\\Sogna\\Sognatore\\src\\Sentinel-Sognatore\\PolicyTypes.ts", "source_location": "L122", "confidence_score": 1.0}, {"id": "policytypes_validatedata", "label": "validateData()", "file_type": "code", "source_file": "C:\\Users\\carle\\Desktop\\Sogna\\Sogna\\Sognatore\\src\\Sentinel-Sognatore\\PolicyTypes.ts", "source_location": "L128", "confidence_score": 1.0}, {"id": "policytypes_validateapprovalgate", "label": "validateApprovalGate()", "file_type": "code", "source_file": "C:\\Users\\carle\\Desktop\\Sogna\\Sogna\\Sognatore\\src\\Sentinel-Sognatore\\PolicyTypes.ts", "source_location": "L134", "confidence_score": 1.0}], "edges": [{"source": "c_users_carle_desktop_sogna_sogna_sognatore_src_sentinel_sognatore_policytypes_ts", "target": "policytypes_evaluaterule", "relation": "contains", "confidence": "EXTRACTED", "confidence_score": 1.0, "audit_reason": null, "source_file": "C:\\Users\\carle\\Desktop\\Sogna\\Sogna\\Sognatore\\src\\Sentinel-Sognatore\\PolicyTypes.ts", "source_location": "L71", "weight": 1.0}, {"source": "c_users_carle_desktop_sogna_sogna_sognatore_src_sentinel_sognatore_policytypes_ts", "target": "policytypes_scancontent", "relation": "contains", "confidence": "EXTRACTED", "confidence_score": 1.0, "audit_reason": null, "source_file": "C:\\Users\\carle\\Desktop\\Sogna\\Sogna\\Sognatore\\src\\Sentinel-Sognatore\\PolicyTypes.ts", "source_location": "L84", "weight": 1.0}, {"source": "c_users_carle_desktop_sogna_sogna_sognatore_src_sentinel_sognatore_policytypes_ts", "target": "policytypes_validatepreexecution", "relation": "contains", "confidence": "EXTRACTED", "confidence_score": 1.0, "audit_reason": null, "source_file": "C:\\Users\\carle\\Desktop\\Sogna\\Sogna\\Sognatore\\src\\Sentinel-Sognatore\\PolicyTypes.ts", "source_location": "L110", "weight": 1.0}, {"source": "c_users_carle_desktop_sogna_sogna_sognatore_src_sentinel_sognatore_policytypes_ts", "target": "policytypes_validatepredeployment", "relation": "contains", "confidence": "EXTRACTED", "confidence_score": 1.0, "audit_reason": null, "source_file": "C:\\Users\\carle\\Desktop\\Sogna\\Sogna\\Sognatore\\src\\Sentinel-Sognatore\\PolicyTypes.ts", "source_location": "L116", "weight": 1.0}, {"source": "c_users_carle_desktop_sogna_sogna_sognatore_src_sentinel_sognatore_policytypes_ts", "target": "policytypes_validateresource", "relation": "contains", "confidence": "EXTRACTED", "confidence_score": 1.0, "audit_reason": null, "source_file": "C:\\Users\\carle\\Desktop\\Sogna\\Sogna\\Sognatore\\src\\Sentinel-Sognatore\\PolicyTypes.ts", "source_location": "L122", "weight": 1.0}, {"source": "c_users_carle_desktop_sogna_sogna_sognatore_src_sentinel_sognatore_policytypes_ts", "target": "policytypes_validatedata", "relation": "contains", "confidence": "EXTRACTED", "confidence_score": 1.0, "audit_reason": null, "source_file": "C:\\Users\\carle\\Desktop\\Sogna\\Sogna\\Sognatore\\src\\Sentinel-Sognatore\\PolicyTypes.ts", "source_location": "L128", "weight": 1.0}, {"source": "c_users_carle_desktop_sogna_sogna_sognatore_src_sentinel_sognatore_policytypes_ts", "target": "policytypes_validateapprovalgate", "relation": "contains", "confidence": "EXTRACTED", "confidence_score": 1.0, "audit_reason": null, "source_file": "C:\\Users\\carle\\Desktop\\Sogna\\Sogna\\Sognatore\\src\\Sentinel-Sognatore\\PolicyTypes.ts", "source_location": "L134", "weight": 1.0}], "raw_calls": [{"caller_nid": "policytypes_evaluaterule", "callee": "evaluator", "source_file": "C:\\Users\\carle\\Desktop\\Sogna\\Sogna\\Sognatore\\src\\Sentinel-Sognatore\\PolicyTypes.ts", "source_location": "L73"}, {"caller_nid": "policytypes_evaluaterule", "callee": "test", "source_file": "C:\\Users\\carle\\Desktop\\Sogna\\Sogna\\Sognatore\\src\\Sentinel-Sognatore\\PolicyTypes.ts", "source_location": "L78"}, {"caller_nid": "policytypes_scancontent", "callee": "match", "source_file": "C:\\Users\\carle\\Desktop\\Sogna\\Sogna\\Sognatore\\src\\Sentinel-Sognatore\\PolicyTypes.ts", "source_location": "L94"}, {"caller_nid": "policytypes_scancontent", "callee": "push", "source_file": "C:\\Users\\carle\\Desktop\\Sogna\\Sogna\\Sognatore\\src\\Sentinel-Sognatore\\PolicyTypes.ts", "source_location": "L95"}, {"caller_nid": "policytypes_validatepreexecution", "callee": "push", "source_file": "C:\\Users\\carle\\Desktop\\Sogna\\Sogna\\Sognatore\\src\\Sentinel-Sognatore\\PolicyTypes.ts", "source_location": "L112"}, {"caller_nid": "policytypes_validatepredeployment", "callee": "push", "source_file": "C:\\Users\\carle\\Desktop\\Sogna\\Sogna\\Sognatore\\src\\Sentinel-Sognatore\\PolicyTypes.ts", "source_location": "L118"}, {"caller_nid": "policytypes_validateresource", "callee": "push", "source_file": "C:\\Users\\carle\\Desktop\\Sogna\\Sogna\\Sognatore\\src\\Sentinel-Sognatore\\PolicyTypes.ts", "source_location": "L124"}, {"caller_nid": "policytypes_validatedata", "callee": "push", "source_file": "C:\\Users\\carle\\Desktop\\Sogna\\Sogna\\Sognatore\\src\\Sentinel-Sognatore\\PolicyTypes.ts", "source_location": "L130"}, {"caller_nid": "policytypes_validateapprovalgate", "callee": "push", "source_file": "C:\\Users\\carle\\Desktop\\Sogna\\Sogna\\Sognatore\\src\\Sentinel-Sognatore\\PolicyTypes.ts", "source_location": "L136"}]}