{"nodes": [{"id": "c_users_carle_desktop_sogna_sogna_curator_engines_animator_dom_types_projection_utils_flat_tree_d_ts", "label": "flat-tree.d.ts", "file_type": "code", "source_file": "C:\\Users\\carle\\Desktop\\Sogna\\Sogna\\Curator\\engines\\Animator\\dom\\types\\projection\\utils\\flat-tree.d.ts", "source_location": "L1", "confidence_score": 1.0}, {"id": "flat_tree_d_flattree", "label": "FlatTree", "file_type": "code", "source_file": "C:\\Users\\carle\\Desktop\\Sogna\\Sogna\\Curator\\engines\\Animator\\dom\\types\\projection\\utils\\flat-tree.d.ts", "source_location": "L2", "confidence_score": 1.0}], "edges": [{"source": "c_users_carle_desktop_sogna_sogna_curator_engines_animator_dom_types_projection_utils_flat_tree_d_ts", "target": "c_users_carle_desktop_sogna_sogna_curator_engines_animator_dom_types_projection_utils_compare_by_depth_ts", "relation": "imports", "confidence": "EXTRACTED", "confidence_score": 1.0, "audit_reason": null, "source_file": "C:\\Users\\carle\\Desktop\\Sogna\\Sogna\\Curator\\engines\\Animator\\dom\\types\\projection\\utils\\flat-tree.d.ts", "source_location": "L1", "weight": 1.0}, {"source": "c_users_carle_desktop_sogna_sogna_curator_engines_animator_dom_types_projection_utils_flat_tree_d_ts", "target": "flat_tree_d_flattree", "relation": "contains", "confidence": "EXTRACTED", "confidence_score": 1.0, "audit_reason": null, "source_file": "C:\\Users\\carle\\Desktop\\Sogna\\Sogna\\Curator\\engines\\Animator\\dom\\types\\projection\\utils\\flat-tree.d.ts", "source_location": "L2", "weight": 1.0}], "raw_calls": []}