{"nodes": [{"id": "c_users_carle_desktop_sogna_sogna_toolkit_engines_assembler_react_src_tools_edit_tool_tsx", "label": "edit-tool.tsx", "file_type": "code", "source_file": "C:\\Users\\carle\\Desktop\\Sogna\\Sogna\\toolkit\\engines\\Assembler\\react\\src\\tools\\edit-tool.tsx", "source_location": "L1"}, {"id": "edit_tool_edittooldiffcard", "label": "EditToolDiffCard()", "file_type": "code", "source_file": "C:\\Users\\carle\\Desktop\\Sogna\\Sogna\\toolkit\\engines\\Assembler\\react\\src\\tools\\edit-tool.tsx", "source_location": "L11"}, {"id": "edit_tool_noop", "label": "noop()", "file_type": "code", "source_file": "C:\\Users\\carle\\Desktop\\Sogna\\Sogna\\toolkit\\engines\\Assembler\\react\\src\\tools\\edit-tool.tsx", "source_location": "L138"}], "edges": [{"source": "c_users_carle_desktop_sogna_sogna_toolkit_engines_assembler_react_src_tools_edit_tool_tsx", "target": "react", "relation": "imports_from", "confidence": "EXTRACTED", "source_file": "C:\\Users\\carle\\Desktop\\Sogna\\Sogna\\toolkit\\engines\\Assembler\\react\\src\\tools\\edit-tool.tsx", "source_location": "L1", "weight": 1.0}, {"source": "c_users_carle_desktop_sogna_sogna_toolkit_engines_assembler_react_src_tools_edit_tool_tsx", "target": "react", "relation": "imports_from", "confidence": "EXTRACTED", "source_file": "C:\\Users\\carle\\Desktop\\Sogna\\Sogna\\toolkit\\engines\\Assembler\\react\\src\\tools\\edit-tool.tsx", "source_location": "L2", "weight": 1.0}, {"source": "c_users_carle_desktop_sogna_sogna_toolkit_engines_assembler_react_src_tools_edit_tool_tsx", "target": "c_users_carle_desktop_sogna_sogna_toolkit_engines_assembler_react_src_components_text_shimmer", "relation": "imports_from", "confidence": "EXTRACTED", "source_file": "C:\\Users\\carle\\Desktop\\Sogna\\Sogna\\toolkit\\engines\\Assembler\\react\\src\\tools\\edit-tool.tsx", "source_location": "L3", "weight": 1.0}, {"source": "c_users_carle_desktop_sogna_sogna_toolkit_engines_assembler_react_src_tools_edit_tool_tsx", "target": "c_users_carle_desktop_sogna_sogna_toolkit_engines_assembler_react_src_types_timeline", "relation": "imports_from", "confidence": "EXTRACTED", "source_file": "C:\\Users\\carle\\Desktop\\Sogna\\Sogna\\toolkit\\engines\\Assembler\\react\\src\\tools\\edit-tool.tsx", "source_location": "L4", "weight": 1.0}, {"source": "c_users_carle_desktop_sogna_sogna_toolkit_engines_assembler_react_src_tools_edit_tool_tsx", "target": "c_users_carle_desktop_sogna_sogna_toolkit_engines_assembler_react_src_types_tool_styles", "relation": "imports_from", "confidence": "EXTRACTED", "source_file": "C:\\Users\\carle\\Desktop\\Sogna\\Sogna\\toolkit\\engines\\Assembler\\react\\src\\tools\\edit-tool.tsx", "source_location": "L5", "weight": 1.0}, {"source": "c_users_carle_desktop_sogna_sogna_toolkit_engines_assembler_react_src_tools_edit_tool_tsx", "target": "c_users_carle_desktop_sogna_sogna_toolkit_engines_assembler_react_src_hooks_use_tool_complete", "relation": "imports_from", "confidence": "EXTRACTED", "source_file": "C:\\Users\\carle\\Desktop\\Sogna\\Sogna\\toolkit\\engines\\Assembler\\react\\src\\tools\\edit-tool.tsx", "source_location": "L6", "weight": 1.0}, {"source": "c_users_carle_desktop_sogna_sogna_toolkit_engines_assembler_react_src_tools_edit_tool_tsx", "target": "c_users_carle_desktop_sogna_sogna_toolkit_engines_assembler_react_src_icons_file_ext_icon", "relation": "imports_from", "confidence": "EXTRACTED", "source_file": "C:\\Users\\carle\\Desktop\\Sogna\\Sogna\\toolkit\\engines\\Assembler\\react\\src\\tools\\edit-tool.tsx", "source_location": "L7", "weight": 1.0}, {"source": "c_users_carle_desktop_sogna_sogna_toolkit_engines_assembler_react_src_tools_edit_tool_tsx", "target": "c_users_carle_desktop_sogna_sogna_toolkit_engines_assembler_react_src_tools_tool_row_base", "relation": "imports_from", "confidence": "EXTRACTED", "source_file": "C:\\Users\\carle\\Desktop\\Sogna\\Sogna\\toolkit\\engines\\Assembler\\react\\src\\tools\\edit-tool.tsx", "source_location": "L8", "weight": 1.0}, {"source": "c_users_carle_desktop_sogna_sogna_toolkit_engines_assembler_react_src_tools_edit_tool_tsx", "target": "c_users_carle_desktop_sogna_sogna_toolkit_engines_assembler_react_src_utils_tool_adapters", "relation": "imports_from", "confidence": "EXTRACTED", "source_file": "C:\\Users\\carle\\Desktop\\Sogna\\Sogna\\toolkit\\engines\\Assembler\\react\\src\\tools\\edit-tool.tsx", "source_location": "L9", "weight": 1.0}, {"source": "c_users_carle_desktop_sogna_sogna_toolkit_engines_assembler_react_src_tools_edit_tool_tsx", "target": "edit_tool_edittooldiffcard", "relation": "contains", "confidence": "EXTRACTED", "source_file": "C:\\Users\\carle\\Desktop\\Sogna\\Sogna\\toolkit\\engines\\Assembler\\react\\src\\tools\\edit-tool.tsx", "source_location": "L11", "weight": 1.0}, {"source": "c_users_carle_desktop_sogna_sogna_toolkit_engines_assembler_react_src_tools_edit_tool_tsx", "target": "edit_tool_noop", "relation": "contains", "confidence": "EXTRACTED", "source_file": "C:\\Users\\carle\\Desktop\\Sogna\\Sogna\\toolkit\\engines\\Assembler\\react\\src\\tools\\edit-tool.tsx", "source_location": "L138", "weight": 1.0}], "raw_calls": [{"caller_nid": "edit_tool_edittooldiffcard", "callee": "useToolComplete", "source_file": "C:\\Users\\carle\\Desktop\\Sogna\\Sogna\\toolkit\\engines\\Assembler\\react\\src\\tools\\edit-tool.tsx", "source_location": "L22"}, {"caller_nid": "edit_tool_edittooldiffcard", "callee": "pop", "source_file": "C:\\Users\\carle\\Desktop\\Sogna\\Sogna\\toolkit\\engines\\Assembler\\react\\src\\tools\\edit-tool.tsx", "source_location": "L24"}, {"caller_nid": "edit_tool_edittooldiffcard", "callee": "split", "source_file": "C:\\Users\\carle\\Desktop\\Sogna\\Sogna\\toolkit\\engines\\Assembler\\react\\src\\tools\\edit-tool.tsx", "source_location": "L24"}]}