{"nodes": [{"id": "c_users_carle_desktop_sogna_sogna_curator_engines_animator_dom_src_scroll_observe_ts", "label": "observe.ts", "file_type": "code", "source_file": "C:\\Users\\carle\\Desktop\\Sogna\\Sogna\\Curator\\engines\\Animator\\dom\\src\\scroll\\observe.ts", "source_location": "L1", "confidence_score": 1.0}, {"id": "observe_observetimeline", "label": "observeTimeline()", "file_type": "code", "source_file": "C:\\Users\\carle\\Desktop\\Sogna\\Sogna\\Curator\\engines\\Animator\\dom\\src\\scroll\\observe.ts", "source_location": "L6", "confidence_score": 1.0}], "edges": [{"source": "c_users_carle_desktop_sogna_sogna_curator_engines_animator_dom_src_scroll_observe_ts", "target": "c_users_carle_desktop_sogna_sogna_curator_engines_animator_dom_src_animation_types_ts", "relation": "imports", "confidence": "EXTRACTED", "confidence_score": 1.0, "audit_reason": null, "source_file": "C:\\Users\\carle\\Desktop\\Sogna\\Sogna\\Curator\\engines\\Animator\\dom\\src\\scroll\\observe.ts", "source_location": "L1", "weight": 1.0}, {"source": "c_users_carle_desktop_sogna_sogna_curator_engines_animator_dom_src_scroll_observe_ts", "target": "c_users_carle_desktop_sogna_sogna_curator_engines_animator_dom_src_frameloop", "relation": "imports", "confidence": "EXTRACTED", "confidence_score": 1.0, "audit_reason": null, "source_file": "C:\\Users\\carle\\Desktop\\Sogna\\Sogna\\Curator\\engines\\Animator\\dom\\src\\scroll\\observe.ts", "source_location": "L2", "weight": 1.0}, {"source": "c_users_carle_desktop_sogna_sogna_curator_engines_animator_dom_src_scroll_observe_ts", "target": "observe_observetimeline", "relation": "contains", "confidence": "EXTRACTED", "confidence_score": 1.0, "audit_reason": null, "source_file": "C:\\Users\\carle\\Desktop\\Sogna\\Sogna\\Curator\\engines\\Animator\\dom\\src\\scroll\\observe.ts", "source_location": "L6", "weight": 1.0}], "raw_calls": [{"caller_nid": "observe_observetimeline", "callee": "preUpdate", "source_file": "C:\\Users\\carle\\Desktop\\Sogna\\Sogna\\Curator\\engines\\Animator\\dom\\src\\scroll\\observe.ts", "source_location": "L21"}]}