{"nodes": [{"id": "c_users_carle_desktop_sogna_sogna_memory_identity_mcp_uma_server_py", "label": "mcp_uma_server.py", "file_type": "code", "source_file": "C:\\Users\\carle\\Desktop\\Sogna\\Sogna\\memory\\identity\\mcp_uma_server.py", "source_location": "L1", "confidence_score": 1.0}, {"id": "mcp_uma_server_semantic_recall", "label": "semantic_recall()", "file_type": "code", "source_file": "C:\\Users\\carle\\Desktop\\Sogna\\Sogna\\memory\\identity\\mcp_uma_server.py", "source_location": "L28", "confidence_score": 1.0}, {"id": "mcp_uma_server_decorator_mcp_tool", "label": "@mcp.tool()", "file_type": "code", "source_file": "C:\\Users\\carle\\Desktop\\Sogna\\Sogna\\memory\\identity\\mcp_uma_server.py", "source_location": "L28", "confidence_score": 1.0}, {"id": "mcp_uma_server_rationale_29", "label": "Realiza una b\u00fasqueda sem\u00e1ntica en la memoria UMA de Sognatore.", "file_type": "rationale", "source_file": "C:\\Users\\carle\\Desktop\\Sogna\\Sogna\\memory\\identity\\mcp_uma_server.py", "source_location": "L29", "confidence_score": 1.0}], "edges": [{"source": "c_users_carle_desktop_sogna_sogna_memory_identity_mcp_uma_server_py", "target": "json", "relation": "imports", "confidence": "EXTRACTED", "confidence_score": 1.0, "audit_reason": null, "source_file": "C:\\Users\\carle\\Desktop\\Sogna\\Sogna\\memory\\identity\\mcp_uma_server.py", "source_location": "L1", "weight": 1.0}, {"source": "c_users_carle_desktop_sogna_sogna_memory_identity_mcp_uma_server_py", "target": "mcp_server_fastmcp", "relation": "imports", "confidence": "EXTRACTED", "confidence_score": 1.0, "audit_reason": null, "source_file": "C:\\Users\\carle\\Desktop\\Sogna\\Sogna\\memory\\identity\\mcp_uma_server.py", "source_location": "L2", "weight": 1.0}, {"source": "c_users_carle_desktop_sogna_sogna_memory_identity_mcp_uma_server_py", "target": "mcp_server_fastmcp", "relation": "imports", "confidence": "EXTRACTED", "confidence_score": 1.0, "audit_reason": null, "source_file": "C:\\Users\\carle\\Desktop\\Sogna\\Sogna\\memory\\identity\\mcp_uma_server.py", "source_location": "L3", "weight": 1.0}, {"source": "c_users_carle_desktop_sogna_sogna_memory_identity_mcp_uma_server_py", "target": "sys", "relation": "imports", "confidence": "EXTRACTED", "confidence_score": 1.0, "audit_reason": null, "source_file": "C:\\Users\\carle\\Desktop\\Sogna\\Sogna\\memory\\identity\\mcp_uma_server.py", "source_location": "L4", "weight": 1.0}, {"source": "c_users_carle_desktop_sogna_sogna_memory_identity_mcp_uma_server_py", "target": "os", "relation": "imports", "confidence": "EXTRACTED", "confidence_score": 1.0, "audit_reason": null, "source_file": "C:\\Users\\carle\\Desktop\\Sogna\\Sogna\\memory\\identity\\mcp_uma_server.py", "source_location": "L5", "weight": 1.0}, {"source": "c_users_carle_desktop_sogna_sogna_memory_identity_mcp_uma_server_py", "target": "logging", "relation": "imports", "confidence": "EXTRACTED", "confidence_score": 1.0, "audit_reason": null, "source_file": "C:\\Users\\carle\\Desktop\\Sogna\\Sogna\\memory\\identity\\mcp_uma_server.py", "source_location": "L6", "weight": 1.0}, {"source": "c_users_carle_desktop_sogna_sogna_memory_identity_mcp_uma_server_py", "target": "query_uma", "relation": "imports", "confidence": "EXTRACTED", "confidence_score": 1.0, "audit_reason": null, "source_file": "C:\\Users\\carle\\Desktop\\Sogna\\Sogna\\memory\\identity\\mcp_uma_server.py", "source_location": "L22", "weight": 1.0}, {"source": "c_users_carle_desktop_sogna_sogna_memory_identity_mcp_uma_server_py", "target": "mcp_uma_server_semantic_recall", "relation": "contains", "confidence": "EXTRACTED", "confidence_score": 1.0, "audit_reason": null, "source_file": "C:\\Users\\carle\\Desktop\\Sogna\\Sogna\\memory\\identity\\mcp_uma_server.py", "source_location": "L28", "weight": 1.0}, {"source": "mcp_uma_server_semantic_recall", "target": "mcp_uma_server_decorator_mcp_tool", "relation": "decorated_by", "confidence": "EXTRACTED", "confidence_score": 1.0, "audit_reason": null, "source_file": "C:\\Users\\carle\\Desktop\\Sogna\\Sogna\\memory\\identity\\mcp_uma_server.py", "source_location": "L28", "weight": 1.0}, {"source": "mcp_uma_server_rationale_29", "target": "mcp_uma_server_semantic_recall", "relation": "rationale_for", "confidence": "EXTRACTED", "confidence_score": 1.0, "audit_reason": "Rationale comment or docstring", "source_file": "C:\\Users\\carle\\Desktop\\Sogna\\Sogna\\memory\\identity\\mcp_uma_server.py", "source_location": "L29", "weight": 1.0}], "raw_calls": [{"caller_nid": "mcp_uma_server_semantic_recall", "callee": "query_hybrid", "source_file": "C:\\Users\\carle\\Desktop\\Sogna\\Sogna\\memory\\identity\\mcp_uma_server.py", "source_location": "L33"}, {"caller_nid": "mcp_uma_server_semantic_recall", "callee": "dumps", "source_file": "C:\\Users\\carle\\Desktop\\Sogna\\Sogna\\memory\\identity\\mcp_uma_server.py", "source_location": "L36"}, {"caller_nid": "mcp_uma_server_semantic_recall", "callee": "str", "source_file": "C:\\Users\\carle\\Desktop\\Sogna\\Sogna\\memory\\identity\\mcp_uma_server.py", "source_location": "L41"}, {"caller_nid": "mcp_uma_server_semantic_recall", "callee": "print", "source_file": "C:\\Users\\carle\\Desktop\\Sogna\\Sogna\\memory\\identity\\mcp_uma_server.py", "source_location": "L42"}]}