{"nodes": [{"id": "c_users_carle_desktop_sogna_sogna_sognatore_src_core_memory_neuralgraft_ts", "label": "NeuralGraft.ts", "file_type": "code", "source_file": "C:\\Users\\carle\\Desktop\\Sogna\\Sogna\\Sognatore\\src\\core\\memory\\NeuralGraft.ts", "source_location": "L1", "confidence_score": 1.0}, {"id": "neuralgraft_systemgraft", "label": "systemGraft", "file_type": "code", "source_file": "C:\\Users\\carle\\Desktop\\Sogna\\Sogna\\Sognatore\\src\\core\\memory\\NeuralGraft.ts", "source_location": "L10", "confidence_score": 1.0}, {"id": "neuralgraft_systemgraft_constructor", "label": ".constructor()", "file_type": "code", "source_file": "C:\\Users\\carle\\Desktop\\Sogna\\Sogna\\Sognatore\\src\\core\\memory\\NeuralGraft.ts", "source_location": "L14", "confidence_score": 1.0}, {"id": "neuralgraft_systemgraft_getinstance", "label": ".getInstance()", "file_type": "code", "source_file": "C:\\Users\\carle\\Desktop\\Sogna\\Sogna\\Sognatore\\src\\core\\memory\\NeuralGraft.ts", "source_location": "L18", "confidence_score": 1.0}, {"id": "neuralgraft_systemgraft_graft", "label": ".graft()", "file_type": "code", "source_file": "C:\\Users\\carle\\Desktop\\Sogna\\Sogna\\Sognatore\\src\\core\\memory\\NeuralGraft.ts", "source_location": "L31", "confidence_score": 1.0}], "edges": [{"source": "c_users_carle_desktop_sogna_sogna_sognatore_src_core_memory_neuralgraft_ts", "target": "curator", "relation": "imports", "confidence": "EXTRACTED", "confidence_score": 1.0, "audit_reason": null, "source_file": "C:\\Users\\carle\\Desktop\\Sogna\\Sogna\\Sognatore\\src\\core\\memory\\NeuralGraft.ts", "source_location": "L1", "weight": 1.0}, {"source": "c_users_carle_desktop_sogna_sogna_sognatore_src_core_memory_neuralgraft_ts", "target": "c_users_carle_desktop_sogna_sogna_sognatore_src_core_memory_memoryhub_ts", "relation": "imports", "confidence": "EXTRACTED", "confidence_score": 1.0, "audit_reason": null, "source_file": "C:\\Users\\carle\\Desktop\\Sogna\\Sogna\\Sognatore\\src\\core\\memory\\NeuralGraft.ts", "source_location": "L2", "weight": 1.0}, {"source": "c_users_carle_desktop_sogna_sogna_sognatore_src_core_memory_neuralgraft_ts", "target": "c_users_carle_desktop_sogna_sogna_sognatore_src_core_memory_chronicler_ts", "relation": "imports", "confidence": "EXTRACTED", "confidence_score": 1.0, "audit_reason": null, "source_file": "C:\\Users\\carle\\Desktop\\Sogna\\Sogna\\Sognatore\\src\\core\\memory\\NeuralGraft.ts", "source_location": "L3", "weight": 1.0}, {"source": "c_users_carle_desktop_sogna_sogna_sognatore_src_core_memory_neuralgraft_ts", "target": "neuralgraft_systemgraft", "relation": "contains", "confidence": "EXTRACTED", "confidence_score": 1.0, "audit_reason": null, "source_file": "C:\\Users\\carle\\Desktop\\Sogna\\Sogna\\Sognatore\\src\\core\\memory\\NeuralGraft.ts", "source_location": "L10", "weight": 1.0}, {"source": "neuralgraft_systemgraft", "target": "neuralgraft_systemgraft_constructor", "relation": "method", "confidence": "EXTRACTED", "confidence_score": 1.0, "audit_reason": null, "source_file": "C:\\Users\\carle\\Desktop\\Sogna\\Sogna\\Sognatore\\src\\core\\memory\\NeuralGraft.ts", "source_location": "L14", "weight": 1.0}, {"source": "neuralgraft_systemgraft", "target": "neuralgraft_systemgraft_getinstance", "relation": "method", "confidence": "EXTRACTED", "confidence_score": 1.0, "audit_reason": null, "source_file": "C:\\Users\\carle\\Desktop\\Sogna\\Sogna\\Sognatore\\src\\core\\memory\\NeuralGraft.ts", "source_location": "L18", "weight": 1.0}, {"source": "neuralgraft_systemgraft", "target": "neuralgraft_systemgraft_graft", "relation": "method", "confidence": "EXTRACTED", "confidence_score": 1.0, "audit_reason": null, "source_file": "C:\\Users\\carle\\Desktop\\Sogna\\Sogna\\Sognatore\\src\\core\\memory\\NeuralGraft.ts", "source_location": "L31", "weight": 1.0}, {"source": "neuralgraft_systemgraft_constructor", "target": "neuralgraft_systemgraft_getinstance", "relation": "calls", "confidence": "EXTRACTED", "confidence_score": 1.0, "audit_reason": null, "source_file": "C:\\Users\\carle\\Desktop\\Sogna\\Sogna\\Sognatore\\src\\core\\memory\\NeuralGraft.ts", "source_location": "L15", "weight": 1.0}, {"source": "neuralgraft_systemgraft_graft", "target": "neuralgraft_systemgraft_getinstance", "relation": "calls", "confidence": "EXTRACTED", "confidence_score": 1.0, "audit_reason": null, "source_file": "C:\\Users\\carle\\Desktop\\Sogna\\Sogna\\Sognatore\\src\\core\\memory\\NeuralGraft.ts", "source_location": "L51", "weight": 1.0}], "raw_calls": [{"caller_nid": "neuralgraft_systemgraft_graft", "callee": "log", "source_file": "C:\\Users\\carle\\Desktop\\Sogna\\Sogna\\Sognatore\\src\\core\\memory\\NeuralGraft.ts", "source_location": "L32"}, {"caller_nid": "neuralgraft_systemgraft_graft", "callee": "blue", "source_file": "C:\\Users\\carle\\Desktop\\Sogna\\Sogna\\Sognatore\\src\\core\\memory\\NeuralGraft.ts", "source_location": "L32"}, {"caller_nid": "neuralgraft_systemgraft_graft", "callee": "storeInsight", "source_file": "C:\\Users\\carle\\Desktop\\Sogna\\Sogna\\Sognatore\\src\\core\\memory\\NeuralGraft.ts", "source_location": "L46"}, {"caller_nid": "neuralgraft_systemgraft_graft", "callee": "toLowerCase", "source_file": "C:\\Users\\carle\\Desktop\\Sogna\\Sogna\\Sognatore\\src\\core\\memory\\NeuralGraft.ts", "source_location": "L46"}, {"caller_nid": "neuralgraft_systemgraft_graft", "callee": "log", "source_file": "C:\\Users\\carle\\Desktop\\Sogna\\Sogna\\Sognatore\\src\\core\\memory\\NeuralGraft.ts", "source_location": "L48"}, {"caller_nid": "neuralgraft_systemgraft_graft", "callee": "green", "source_file": "C:\\Users\\carle\\Desktop\\Sogna\\Sogna\\Sognatore\\src\\core\\memory\\NeuralGraft.ts", "source_location": "L48"}, {"caller_nid": "neuralgraft_systemgraft_graft", "callee": "rebuildIndex", "source_file": "C:\\Users\\carle\\Desktop\\Sogna\\Sogna\\Sognatore\\src\\core\\memory\\NeuralGraft.ts", "source_location": "L51"}]}