{"nodes": [{"id": "c_users_carle_desktop_sogna_sogna_curator_bin_pulse_js", "label": "pulse.js", "file_type": "code", "source_file": "C:\\Users\\carle\\Desktop\\Sogna\\Sogna\\Curator\\bin\\pulse.js", "source_location": "L1", "confidence_score": 1.0}, {"id": "pulse_checksystem", "label": "checkSystem()", "file_type": "code", "source_file": "C:\\Users\\carle\\Desktop\\Sogna\\Sogna\\Curator\\bin\\pulse.js", "source_location": "L18", "confidence_score": 1.0}], "edges": [{"source": "c_users_carle_desktop_sogna_sogna_curator_bin_pulse_js", "target": "fs", "relation": "imports", "confidence": "EXTRACTED", "confidence_score": 1.0, "audit_reason": null, "source_file": "C:\\Users\\carle\\Desktop\\Sogna\\Sogna\\Curator\\bin\\pulse.js", "source_location": "L1", "weight": 1.0}, {"source": "c_users_carle_desktop_sogna_sogna_curator_bin_pulse_js", "target": "path", "relation": "imports", "confidence": "EXTRACTED", "confidence_score": 1.0, "audit_reason": null, "source_file": "C:\\Users\\carle\\Desktop\\Sogna\\Sogna\\Curator\\bin\\pulse.js", "source_location": "L2", "weight": 1.0}, {"source": "c_users_carle_desktop_sogna_sogna_curator_bin_pulse_js", "target": "pulse_checksystem", "relation": "contains", "confidence": "EXTRACTED", "confidence_score": 1.0, "audit_reason": null, "source_file": "C:\\Users\\carle\\Desktop\\Sogna\\Sogna\\Curator\\bin\\pulse.js", "source_location": "L18", "weight": 1.0}], "raw_calls": [{"caller_nid": "pulse_checksystem", "callee": "cwd", "source_file": "C:\\Users\\carle\\Desktop\\Sogna\\Sogna\\Curator\\bin\\pulse.js", "source_location": "L19"}, {"caller_nid": "pulse_checksystem", "callee": "log", "source_file": "C:\\Users\\carle\\Desktop\\Sogna\\Sogna\\Curator\\bin\\pulse.js", "source_location": "L20"}, {"caller_nid": "pulse_checksystem", "callee": "toISOString", "source_file": "C:\\Users\\carle\\Desktop\\Sogna\\Sogna\\Curator\\bin\\pulse.js", "source_location": "L23"}, {"caller_nid": "pulse_checksystem", "callee": "existsSync", "source_file": "C:\\Users\\carle\\Desktop\\Sogna\\Sogna\\Curator\\bin\\pulse.js", "source_location": "L30"}, {"caller_nid": "pulse_checksystem", "callee": "join", "source_file": "C:\\Users\\carle\\Desktop\\Sogna\\Sogna\\Curator\\bin\\pulse.js", "source_location": "L30"}, {"caller_nid": "pulse_checksystem", "callee": "error", "source_file": "C:\\Users\\carle\\Desktop\\Sogna\\Sogna\\Curator\\bin\\pulse.js", "source_location": "L31"}, {"caller_nid": "pulse_checksystem", "callee": "existsSync", "source_file": "C:\\Users\\carle\\Desktop\\Sogna\\Sogna\\Curator\\bin\\pulse.js", "source_location": "L38"}, {"caller_nid": "pulse_checksystem", "callee": "join", "source_file": "C:\\Users\\carle\\Desktop\\Sogna\\Sogna\\Curator\\bin\\pulse.js", "source_location": "L38"}, {"caller_nid": "pulse_checksystem", "callee": "push", "source_file": "C:\\Users\\carle\\Desktop\\Sogna\\Sogna\\Curator\\bin\\pulse.js", "source_location": "L39"}, {"caller_nid": "pulse_checksystem", "callee": "log", "source_file": "C:\\Users\\carle\\Desktop\\Sogna\\Sogna\\Curator\\bin\\pulse.js", "source_location": "L42"}, {"caller_nid": "pulse_checksystem", "callee": "log", "source_file": "C:\\Users\\carle\\Desktop\\Sogna\\Sogna\\Curator\\bin\\pulse.js", "source_location": "L43"}, {"caller_nid": "pulse_checksystem", "callee": "stringify", "source_file": "C:\\Users\\carle\\Desktop\\Sogna\\Sogna\\Curator\\bin\\pulse.js", "source_location": "L43"}, {"caller_nid": "pulse_checksystem", "callee": "log", "source_file": "C:\\Users\\carle\\Desktop\\Sogna\\Sogna\\Curator\\bin\\pulse.js", "source_location": "L44"}, {"caller_nid": "pulse_checksystem", "callee": "log", "source_file": "C:\\Users\\carle\\Desktop\\Sogna\\Sogna\\Curator\\bin\\pulse.js", "source_location": "L47"}, {"caller_nid": "pulse_checksystem", "callee": "log", "source_file": "C:\\Users\\carle\\Desktop\\Sogna\\Sogna\\Curator\\bin\\pulse.js", "source_location": "L49"}]}