{"nodes": [{"id": "c_users_carle_desktop_sogna_sogna_sognatore_cerebro_optimizer_ts", "label": "CEREBRO_OPTIMIZER.ts", "file_type": "code", "source_file": "C:\\Users\\carle\\Desktop\\Sogna\\Sogna\\Sognatore\\CEREBRO_OPTIMIZER.ts", "source_location": "L1"}, {"id": "cerebro_optimizer_performdeepaudit", "label": "performDeepAudit()", "file_type": "code", "source_file": "C:\\Users\\carle\\Desktop\\Sogna\\Sogna\\Sognatore\\CEREBRO_OPTIMIZER.ts", "source_location": "L9"}], "edges": [{"source": "c_users_carle_desktop_sogna_sogna_sognatore_cerebro_optimizer_ts", "target": "c_users_carle_desktop_sogna_sogna_sognatore_src_core_memory_memoryhub_ts", "relation": "imports_from", "confidence": "EXTRACTED", "source_file": "C:\\Users\\carle\\Desktop\\Sogna\\Sogna\\Sognatore\\CEREBRO_OPTIMIZER.ts", "source_location": "L1", "weight": 1.0}, {"source": "c_users_carle_desktop_sogna_sogna_sognatore_cerebro_optimizer_ts", "target": "c_users_carle_desktop_sogna_sogna_sognatore_src_core_memory_chronicler_ts", "relation": "imports_from", "confidence": "EXTRACTED", "source_file": "C:\\Users\\carle\\Desktop\\Sogna\\Sogna\\Sognatore\\CEREBRO_OPTIMIZER.ts", "source_location": "L2", "weight": 1.0}, {"source": "c_users_carle_desktop_sogna_sogna_sognatore_cerebro_optimizer_ts", "target": "fs_extra", "relation": "imports_from", "confidence": "EXTRACTED", "source_file": "C:\\Users\\carle\\Desktop\\Sogna\\Sogna\\Sognatore\\CEREBRO_OPTIMIZER.ts", "source_location": "L3", "weight": 1.0}, {"source": "c_users_carle_desktop_sogna_sogna_sognatore_cerebro_optimizer_ts", "target": "path", "relation": "imports_from", "confidence": "EXTRACTED", "source_file": "C:\\Users\\carle\\Desktop\\Sogna\\Sogna\\Sognatore\\CEREBRO_OPTIMIZER.ts", "source_location": "L4", "weight": 1.0}, {"source": "c_users_carle_desktop_sogna_sogna_sognatore_cerebro_optimizer_ts", "target": "chalk", "relation": "imports_from", "confidence": "EXTRACTED", "source_file": "C:\\Users\\carle\\Desktop\\Sogna\\Sogna\\Sognatore\\CEREBRO_OPTIMIZER.ts", "source_location": "L5", "weight": 1.0}, {"source": "c_users_carle_desktop_sogna_sogna_sognatore_cerebro_optimizer_ts", "target": "crypto", "relation": "imports_from", "confidence": "EXTRACTED", "source_file": "C:\\Users\\carle\\Desktop\\Sogna\\Sogna\\Sognatore\\CEREBRO_OPTIMIZER.ts", "source_location": "L6", "weight": 1.0}, {"source": "c_users_carle_desktop_sogna_sogna_sognatore_cerebro_optimizer_ts", "target": "cerebro_optimizer_performdeepaudit", "relation": "contains", "confidence": "EXTRACTED", "source_file": "C:\\Users\\carle\\Desktop\\Sogna\\Sogna\\Sognatore\\CEREBRO_OPTIMIZER.ts", "source_location": "L9", "weight": 1.0}], "raw_calls": [{"caller_nid": "cerebro_optimizer_performdeepaudit", "callee": "log", "source_file": "C:\\Users\\carle\\Desktop\\Sogna\\Sogna\\Sognatore\\CEREBRO_OPTIMIZER.ts", "source_location": "L10"}, {"caller_nid": "cerebro_optimizer_performdeepaudit", "callee": "blue", "source_file": "C:\\Users\\carle\\Desktop\\Sogna\\Sogna\\Sognatore\\CEREBRO_OPTIMIZER.ts", "source_location": "L10"}, {"caller_nid": "cerebro_optimizer_performdeepaudit", "callee": "getInstance", "source_file": "C:\\Users\\carle\\Desktop\\Sogna\\Sogna\\Sognatore\\CEREBRO_OPTIMIZER.ts", "source_location": "L12"}, {"caller_nid": "cerebro_optimizer_performdeepaudit", "callee": "getInstance", "source_file": "C:\\Users\\carle\\Desktop\\Sogna\\Sogna\\Sognatore\\CEREBRO_OPTIMIZER.ts", "source_location": "L13"}, {"caller_nid": "cerebro_optimizer_performdeepaudit", "callee": "log", "source_file": "C:\\Users\\carle\\Desktop\\Sogna\\Sogna\\Sognatore\\CEREBRO_OPTIMIZER.ts", "source_location": "L15"}, {"caller_nid": "cerebro_optimizer_performdeepaudit", "callee": "cyan", "source_file": "C:\\Users\\carle\\Desktop\\Sogna\\Sogna\\Sognatore\\CEREBRO_OPTIMIZER.ts", "source_location": "L15"}, {"caller_nid": "cerebro_optimizer_performdeepaudit", "callee": "rebuildIndex", "source_file": "C:\\Users\\carle\\Desktop\\Sogna\\Sogna\\Sognatore\\CEREBRO_OPTIMIZER.ts", "source_location": "L16"}, {"caller_nid": "cerebro_optimizer_performdeepaudit", "callee": "getIndex", "source_file": "C:\\Users\\carle\\Desktop\\Sogna\\Sogna\\Sognatore\\CEREBRO_OPTIMIZER.ts", "source_location": "L18"}, {"caller_nid": "cerebro_optimizer_performdeepaudit", "callee": "getNeuralGraph", "source_file": "C:\\Users\\carle\\Desktop\\Sogna\\Sogna\\Sognatore\\CEREBRO_OPTIMIZER.ts", "source_location": "L20"}, {"caller_nid": "cerebro_optimizer_performdeepaudit", "callee": "log", "source_file": "C:\\Users\\carle\\Desktop\\Sogna\\Sogna\\Sognatore\\CEREBRO_OPTIMIZER.ts", "source_location": "L23"}, {"caller_nid": "cerebro_optimizer_performdeepaudit", "callee": "yellow", "source_file": "C:\\Users\\carle\\Desktop\\Sogna\\Sogna\\Sognatore\\CEREBRO_OPTIMIZER.ts", "source_location": "L23"}, {"caller_nid": "cerebro_optimizer_performdeepaudit", "callee": "stat", "source_file": "C:\\Users\\carle\\Desktop\\Sogna\\Sogna\\Sognatore\\CEREBRO_OPTIMIZER.ts", "source_location": "L24"}, {"caller_nid": "cerebro_optimizer_performdeepaudit", "callee": "getIndexFile", "source_file": "C:\\Users\\carle\\Desktop\\Sogna\\Sogna\\Sognatore\\CEREBRO_OPTIMIZER.ts", "source_location": "L24"}, {"caller_nid": "cerebro_optimizer_performdeepaudit", "callee": "log", "source_file": "C:\\Users\\carle\\Desktop\\Sogna\\Sogna\\Sognatore\\CEREBRO_OPTIMIZER.ts", "source_location": "L25"}, {"caller_nid": "cerebro_optimizer_performdeepaudit", "callee": "toFixed", "source_file": "C:\\Users\\carle\\Desktop\\Sogna\\Sogna\\Sognatore\\CEREBRO_OPTIMIZER.ts", "source_location": "L25"}, {"caller_nid": "cerebro_optimizer_performdeepaudit", "callee": "now", "source_file": "C:\\Users\\carle\\Desktop\\Sogna\\Sogna\\Sognatore\\CEREBRO_OPTIMIZER.ts", "source_location": "L27"}, {"caller_nid": "cerebro_optimizer_performdeepaudit", "callee": "getNeuralGraph", "source_file": "C:\\Users\\carle\\Desktop\\Sogna\\Sogna\\Sognatore\\CEREBRO_OPTIMIZER.ts", "source_location": "L28"}, {"caller_nid": "cerebro_optimizer_performdeepaudit", "callee": "now", "source_file": "C:\\Users\\carle\\Desktop\\Sogna\\Sogna\\Sognatore\\CEREBRO_OPTIMIZER.ts", "source_location": "L29"}, {"caller_nid": "cerebro_optimizer_performdeepaudit", "callee": "log", "source_file": "C:\\Users\\carle\\Desktop\\Sogna\\Sogna\\Sognatore\\CEREBRO_OPTIMIZER.ts", "source_location": "L30"}, {"caller_nid": "cerebro_optimizer_performdeepaudit", "callee": "red", "source_file": "C:\\Users\\carle\\Desktop\\Sogna\\Sogna\\Sognatore\\CEREBRO_OPTIMIZER.ts", "source_location": "L30"}, {"caller_nid": "cerebro_optimizer_performdeepaudit", "callee": "green", "source_file": "C:\\Users\\carle\\Desktop\\Sogna\\Sogna\\Sognatore\\CEREBRO_OPTIMIZER.ts", "source_location": "L30"}, {"caller_nid": "cerebro_optimizer_performdeepaudit", "callee": "log", "source_file": "C:\\Users\\carle\\Desktop\\Sogna\\Sogna\\Sognatore\\CEREBRO_OPTIMIZER.ts", "source_location": "L33"}, {"caller_nid": "cerebro_optimizer_performdeepaudit", "callee": "yellow", "source_file": "C:\\Users\\carle\\Desktop\\Sogna\\Sogna\\Sognatore\\CEREBRO_OPTIMIZER.ts", "source_location": "L33"}, {"caller_nid": "cerebro_optimizer_performdeepaudit", "callee": "filter", "source_file": "C:\\Users\\carle\\Desktop\\Sogna\\Sogna\\Sognatore\\CEREBRO_OPTIMIZER.ts", "source_location": "L34"}, {"caller_nid": "cerebro_optimizer_performdeepaudit", "callee": "log", "source_file": "C:\\Users\\carle\\Desktop\\Sogna\\Sogna\\Sognatore\\CEREBRO_OPTIMIZER.ts", "source_location": "L38"}, {"caller_nid": "cerebro_optimizer_performdeepaudit", "callee": "toFixed", "source_file": "C:\\Users\\carle\\Desktop\\Sogna\\Sogna\\Sognatore\\CEREBRO_OPTIMIZER.ts", "source_location": "L38"}, {"caller_nid": "cerebro_optimizer_performdeepaudit", "callee": "log", "source_file": "C:\\Users\\carle\\Desktop\\Sogna\\Sogna\\Sognatore\\CEREBRO_OPTIMIZER.ts", "source_location": "L39"}, {"caller_nid": "cerebro_optimizer_performdeepaudit", "callee": "red", "source_file": "C:\\Users\\carle\\Desktop\\Sogna\\Sogna\\Sognatore\\CEREBRO_OPTIMIZER.ts", "source_location": "L39"}, {"caller_nid": "cerebro_optimizer_performdeepaudit", "callee": "log", "source_file": "C:\\Users\\carle\\Desktop\\Sogna\\Sogna\\Sognatore\\CEREBRO_OPTIMIZER.ts", "source_location": "L42"}, {"caller_nid": "cerebro_optimizer_performdeepaudit", "callee": "yellow", "source_file": "C:\\Users\\carle\\Desktop\\Sogna\\Sogna\\Sognatore\\CEREBRO_OPTIMIZER.ts", "source_location": "L42"}, {"caller_nid": "cerebro_optimizer_performdeepaudit", "callee": "forEach", "source_file": "C:\\Users\\carle\\Desktop\\Sogna\\Sogna\\Sognatore\\CEREBRO_OPTIMIZER.ts", "source_location": "L47"}, {"caller_nid": "cerebro_optimizer_performdeepaudit", "callee": "log", "source_file": "C:\\Users\\carle\\Desktop\\Sogna\\Sogna\\Sognatore\\CEREBRO_OPTIMIZER.ts", "source_location": "L54"}, {"caller_nid": "cerebro_optimizer_performdeepaudit", "callee": "toFixed", "source_file": "C:\\Users\\carle\\Desktop\\Sogna\\Sogna\\Sognatore\\CEREBRO_OPTIMIZER.ts", "source_location": "L54"}, {"caller_nid": "cerebro_optimizer_performdeepaudit", "callee": "log", "source_file": "C:\\Users\\carle\\Desktop\\Sogna\\Sogna\\Sognatore\\CEREBRO_OPTIMIZER.ts", "source_location": "L55"}, {"caller_nid": "cerebro_optimizer_performdeepaudit", "callee": "log", "source_file": "C:\\Users\\carle\\Desktop\\Sogna\\Sogna\\Sognatore\\CEREBRO_OPTIMIZER.ts", "source_location": "L56"}, {"caller_nid": "cerebro_optimizer_performdeepaudit", "callee": "yellow", "source_file": "C:\\Users\\carle\\Desktop\\Sogna\\Sogna\\Sognatore\\CEREBRO_OPTIMIZER.ts", "source_location": "L56"}, {"caller_nid": "cerebro_optimizer_performdeepaudit", "callee": "log", "source_file": "C:\\Users\\carle\\Desktop\\Sogna\\Sogna\\Sognatore\\CEREBRO_OPTIMIZER.ts", "source_location": "L59"}, {"caller_nid": "cerebro_optimizer_performdeepaudit", "callee": "yellow", "source_file": "C:\\Users\\carle\\Desktop\\Sogna\\Sogna\\Sognatore\\CEREBRO_OPTIMIZER.ts", "source_location": "L59"}, {"caller_nid": "cerebro_optimizer_performdeepaudit", "callee": "resolve", "source_file": "C:\\Users\\carle\\Desktop\\Sogna\\Sogna\\Sognatore\\CEREBRO_OPTIMIZER.ts", "source_location": "L60"}, {"caller_nid": "cerebro_optimizer_performdeepaudit", "callee": "pathExists", "source_file": "C:\\Users\\carle\\Desktop\\Sogna\\Sogna\\Sognatore\\CEREBRO_OPTIMIZER.ts", "source_location": "L61"}, {"caller_nid": "cerebro_optimizer_performdeepaudit", "callee": "readJson", "source_file": "C:\\Users\\carle\\Desktop\\Sogna\\Sogna\\Sognatore\\CEREBRO_OPTIMIZER.ts", "source_location": "L62"}, {"caller_nid": "cerebro_optimizer_performdeepaudit", "callee": "keys", "source_file": "C:\\Users\\carle\\Desktop\\Sogna\\Sogna\\Sognatore\\CEREBRO_OPTIMIZER.ts", "source_location": "L63"}, {"caller_nid": "cerebro_optimizer_performdeepaudit", "callee": "log", "source_file": "C:\\Users\\carle\\Desktop\\Sogna\\Sogna\\Sognatore\\CEREBRO_OPTIMIZER.ts", "source_location": "L64"}, {"caller_nid": "cerebro_optimizer_performdeepaudit", "callee": "replace", "source_file": "C:\\Users\\carle\\Desktop\\Sogna\\Sogna\\Sognatore\\CEREBRO_OPTIMIZER.ts", "source_location": "L70"}, {"caller_nid": "cerebro_optimizer_performdeepaudit", "callee": "replace", "source_file": "C:\\Users\\carle\\Desktop\\Sogna\\Sogna\\Sognatore\\CEREBRO_OPTIMIZER.ts", "source_location": "L71"}, {"caller_nid": "cerebro_optimizer_performdeepaudit", "callee": "push", "source_file": "C:\\Users\\carle\\Desktop\\Sogna\\Sogna\\Sognatore\\CEREBRO_OPTIMIZER.ts", "source_location": "L84"}, {"caller_nid": "cerebro_optimizer_performdeepaudit", "callee": "join", "source_file": "C:\\Users\\carle\\Desktop\\Sogna\\Sogna\\Sognatore\\CEREBRO_OPTIMIZER.ts", "source_location": "L89"}, {"caller_nid": "cerebro_optimizer_performdeepaudit", "callee": "cwd", "source_file": "C:\\Users\\carle\\Desktop\\Sogna\\Sogna\\Sognatore\\CEREBRO_OPTIMIZER.ts", "source_location": "L89"}, {"caller_nid": "cerebro_optimizer_performdeepaudit", "callee": "replace", "source_file": "C:\\Users\\carle\\Desktop\\Sogna\\Sogna\\Sognatore\\CEREBRO_OPTIMIZER.ts", "source_location": "L89"}, {"caller_nid": "cerebro_optimizer_performdeepaudit", "callee": "existsSync", "source_file": "C:\\Users\\carle\\Desktop\\Sogna\\Sogna\\Sognatore\\CEREBRO_OPTIMIZER.ts", "source_location": "L90"}, {"caller_nid": "cerebro_optimizer_performdeepaudit", "callee": "readFileSync", "source_file": "C:\\Users\\carle\\Desktop\\Sogna\\Sogna\\Sognatore\\CEREBRO_OPTIMIZER.ts", "source_location": "L91"}, {"caller_nid": "cerebro_optimizer_performdeepaudit", "callee": "digest", "source_file": "C:\\Users\\carle\\Desktop\\Sogna\\Sogna\\Sognatore\\CEREBRO_OPTIMIZER.ts", "source_location": "L92"}, {"caller_nid": "cerebro_optimizer_performdeepaudit", "callee": "update", "source_file": "C:\\Users\\carle\\Desktop\\Sogna\\Sogna\\Sognatore\\CEREBRO_OPTIMIZER.ts", "source_location": "L92"}, {"caller_nid": "cerebro_optimizer_performdeepaudit", "callee": "createHash", "source_file": "C:\\Users\\carle\\Desktop\\Sogna\\Sogna\\Sognatore\\CEREBRO_OPTIMIZER.ts", "source_location": "L92"}, {"caller_nid": "cerebro_optimizer_performdeepaudit", "callee": "push", "source_file": "C:\\Users\\carle\\Desktop\\Sogna\\Sogna\\Sognatore\\CEREBRO_OPTIMIZER.ts", "source_location": "L94"}, {"caller_nid": "cerebro_optimizer_performdeepaudit", "callee": "log", "source_file": "C:\\Users\\carle\\Desktop\\Sogna\\Sogna\\Sognatore\\CEREBRO_OPTIMIZER.ts", "source_location": "L100"}, {"caller_nid": "cerebro_optimizer_performdeepaudit", "callee": "red", "source_file": "C:\\Users\\carle\\Desktop\\Sogna\\Sogna\\Sognatore\\CEREBRO_OPTIMIZER.ts", "source_location": "L100"}, {"caller_nid": "cerebro_optimizer_performdeepaudit", "callee": "join", "source_file": "C:\\Users\\carle\\Desktop\\Sogna\\Sogna\\Sognatore\\CEREBRO_OPTIMIZER.ts", "source_location": "L100"}, {"caller_nid": "cerebro_optimizer_performdeepaudit", "callee": "log", "source_file": "C:\\Users\\carle\\Desktop\\Sogna\\Sogna\\Sognatore\\CEREBRO_OPTIMIZER.ts", "source_location": "L102"}, {"caller_nid": "cerebro_optimizer_performdeepaudit", "callee": "green", "source_file": "C:\\Users\\carle\\Desktop\\Sogna\\Sogna\\Sognatore\\CEREBRO_OPTIMIZER.ts", "source_location": "L102"}, {"caller_nid": "cerebro_optimizer_performdeepaudit", "callee": "log", "source_file": "C:\\Users\\carle\\Desktop\\Sogna\\Sogna\\Sognatore\\CEREBRO_OPTIMIZER.ts", "source_location": "L107"}, {"caller_nid": "cerebro_optimizer_performdeepaudit", "callee": "blue", "source_file": "C:\\Users\\carle\\Desktop\\Sogna\\Sogna\\Sognatore\\CEREBRO_OPTIMIZER.ts", "source_location": "L107"}]}