{"nodes": [{"id": "c_users_carle_desktop_sogna_sogna_sognatore_src_audit_complianceengine_ts", "label": "ComplianceEngine.ts", "file_type": "code", "source_file": "C:\\Users\\carle\\Desktop\\Sogna\\Sogna\\Sognatore\\src\\audit\\ComplianceEngine.ts", "source_location": "L1", "confidence_score": 1.0}, {"id": "complianceengine_complianceengine", "label": "ComplianceEngine", "file_type": "code", "source_file": "C:\\Users\\carle\\Desktop\\Sogna\\Sogna\\Sognatore\\src\\audit\\ComplianceEngine.ts", "source_location": "L67", "confidence_score": 1.0}, {"id": "complianceengine_complianceengine_generatesoc2report", "label": ".generateSoc2Report()", "file_type": "code", "source_file": "C:\\Users\\carle\\Desktop\\Sogna\\Sogna\\Sognatore\\src\\audit\\ComplianceEngine.ts", "source_location": "L68", "confidence_score": 1.0}, {"id": "complianceengine_complianceengine_generateiso27001report", "label": ".generateIso27001Report()", "file_type": "code", "source_file": "C:\\Users\\carle\\Desktop\\Sogna\\Sogna\\Sognatore\\src\\audit\\ComplianceEngine.ts", "source_location": "L109", "confidence_score": 1.0}, {"id": "complianceengine_complianceengine_generategdprreport", "label": ".generateGdprReport()", "file_type": "code", "source_file": "C:\\Users\\carle\\Desktop\\Sogna\\Sogna\\Sognatore\\src\\audit\\ComplianceEngine.ts", "source_location": "L147", "confidence_score": 1.0}, {"id": "complianceengine_complianceengine_exportreportjson", "label": ".exportReportJson()", "file_type": "code", "source_file": "C:\\Users\\carle\\Desktop\\Sogna\\Sogna\\Sognatore\\src\\audit\\ComplianceEngine.ts", "source_location": "L187", "confidence_score": 1.0}], "edges": [{"source": "c_users_carle_desktop_sogna_sogna_sognatore_src_audit_complianceengine_ts", "target": "c_users_carle_desktop_sogna_sogna_sognatore_src_audit_audittypes_ts", "relation": "imports", "confidence": "EXTRACTED", "confidence_score": 1.0, "audit_reason": null, "source_file": "C:\\Users\\carle\\Desktop\\Sogna\\Sogna\\Sognatore\\src\\audit\\ComplianceEngine.ts", "source_location": "L1", "weight": 1.0}, {"source": "c_users_carle_desktop_sogna_sogna_sognatore_src_audit_complianceengine_ts", "target": "complianceengine_complianceengine", "relation": "contains", "confidence": "EXTRACTED", "confidence_score": 1.0, "audit_reason": null, "source_file": "C:\\Users\\carle\\Desktop\\Sogna\\Sogna\\Sognatore\\src\\audit\\ComplianceEngine.ts", "source_location": "L67", "weight": 1.0}, {"source": "complianceengine_complianceengine", "target": "complianceengine_complianceengine_generatesoc2report", "relation": "method", "confidence": "EXTRACTED", "confidence_score": 1.0, "audit_reason": null, "source_file": "C:\\Users\\carle\\Desktop\\Sogna\\Sogna\\Sognatore\\src\\audit\\ComplianceEngine.ts", "source_location": "L68", "weight": 1.0}, {"source": "complianceengine_complianceengine", "target": "complianceengine_complianceengine_generateiso27001report", "relation": "method", "confidence": "EXTRACTED", "confidence_score": 1.0, "audit_reason": null, "source_file": "C:\\Users\\carle\\Desktop\\Sogna\\Sogna\\Sognatore\\src\\audit\\ComplianceEngine.ts", "source_location": "L109", "weight": 1.0}, {"source": "complianceengine_complianceengine", "target": "complianceengine_complianceengine_generategdprreport", "relation": "method", "confidence": "EXTRACTED", "confidence_score": 1.0, "audit_reason": null, "source_file": "C:\\Users\\carle\\Desktop\\Sogna\\Sogna\\Sognatore\\src\\audit\\ComplianceEngine.ts", "source_location": "L147", "weight": 1.0}, {"source": "complianceengine_complianceengine", "target": "complianceengine_complianceengine_exportreportjson", "relation": "method", "confidence": "EXTRACTED", "confidence_score": 1.0, "audit_reason": null, "source_file": "C:\\Users\\carle\\Desktop\\Sogna\\Sogna\\Sognatore\\src\\audit\\ComplianceEngine.ts", "source_location": "L187", "weight": 1.0}], "raw_calls": [{"caller_nid": "complianceengine_complianceengine_generatesoc2report", "callee": "forEach", "source_file": "C:\\Users\\carle\\Desktop\\Sogna\\Sogna\\Sognatore\\src\\audit\\ComplianceEngine.ts", "source_location": "L72"}, {"caller_nid": "complianceengine_complianceengine_generatesoc2report", "callee": "keys", "source_file": "C:\\Users\\carle\\Desktop\\Sogna\\Sogna\\Sognatore\\src\\audit\\ComplianceEngine.ts", "source_location": "L72"}, {"caller_nid": "complianceengine_complianceengine_generatesoc2report", "callee": "push", "source_file": "C:\\Users\\carle\\Desktop\\Sogna\\Sogna\\Sognatore\\src\\audit\\ComplianceEngine.ts", "source_location": "L87"}, {"caller_nid": "complianceengine_complianceengine_generatesoc2report", "callee": "toISOString", "source_file": "C:\\Users\\carle\\Desktop\\Sogna\\Sogna\\Sognatore\\src\\audit\\ComplianceEngine.ts", "source_location": "L100"}, {"caller_nid": "complianceengine_complianceengine_generateiso27001report", "callee": "forEach", "source_file": "C:\\Users\\carle\\Desktop\\Sogna\\Sogna\\Sognatore\\src\\audit\\ComplianceEngine.ts", "source_location": "L112"}, {"caller_nid": "complianceengine_complianceengine_generateiso27001report", "callee": "keys", "source_file": "C:\\Users\\carle\\Desktop\\Sogna\\Sogna\\Sognatore\\src\\audit\\ComplianceEngine.ts", "source_location": "L112"}, {"caller_nid": "complianceengine_complianceengine_generateiso27001report", "callee": "push", "source_file": "C:\\Users\\carle\\Desktop\\Sogna\\Sogna\\Sognatore\\src\\audit\\ComplianceEngine.ts", "source_location": "L126"}, {"caller_nid": "complianceengine_complianceengine_generateiso27001report", "callee": "toISOString", "source_file": "C:\\Users\\carle\\Desktop\\Sogna\\Sogna\\Sognatore\\src\\audit\\ComplianceEngine.ts", "source_location": "L139"}, {"caller_nid": "complianceengine_complianceengine_generategdprreport", "callee": "add", "source_file": "C:\\Users\\carle\\Desktop\\Sogna\\Sogna\\Sognatore\\src\\audit\\ComplianceEngine.ts", "source_location": "L158"}, {"caller_nid": "complianceengine_complianceengine_generategdprreport", "callee": "String", "source_file": "C:\\Users\\carle\\Desktop\\Sogna\\Sogna\\Sognatore\\src\\audit\\ComplianceEngine.ts", "source_location": "L158"}, {"caller_nid": "complianceengine_complianceengine_generategdprreport", "callee": "add", "source_file": "C:\\Users\\carle\\Desktop\\Sogna\\Sogna\\Sognatore\\src\\audit\\ComplianceEngine.ts", "source_location": "L161"}, {"caller_nid": "complianceengine_complianceengine_generategdprreport", "callee": "toISOString", "source_file": "C:\\Users\\carle\\Desktop\\Sogna\\Sogna\\Sognatore\\src\\audit\\ComplianceEngine.ts", "source_location": "L168"}, {"caller_nid": "complianceengine_complianceengine_generategdprreport", "callee": "map", "source_file": "C:\\Users\\carle\\Desktop\\Sogna\\Sogna\\Sognatore\\src\\audit\\ComplianceEngine.ts", "source_location": "L173"}, {"caller_nid": "complianceengine_complianceengine_generategdprreport", "callee": "keys", "source_file": "C:\\Users\\carle\\Desktop\\Sogna\\Sogna\\Sognatore\\src\\audit\\ComplianceEngine.ts", "source_location": "L173"}, {"caller_nid": "complianceengine_complianceengine_generategdprreport", "callee": "map", "source_file": "C:\\Users\\carle\\Desktop\\Sogna\\Sogna\\Sognatore\\src\\audit\\ComplianceEngine.ts", "source_location": "L174"}, {"caller_nid": "complianceengine_complianceengine_generategdprreport", "callee": "keys", "source_file": "C:\\Users\\carle\\Desktop\\Sogna\\Sogna\\Sognatore\\src\\audit\\ComplianceEngine.ts", "source_location": "L174"}, {"caller_nid": "complianceengine_complianceengine_generategdprreport", "callee": "from", "source_file": "C:\\Users\\carle\\Desktop\\Sogna\\Sogna\\Sognatore\\src\\audit\\ComplianceEngine.ts", "source_location": "L175"}, {"caller_nid": "complianceengine_complianceengine_exportreportjson", "callee": "stringify", "source_file": "C:\\Users\\carle\\Desktop\\Sogna\\Sogna\\Sognatore\\src\\audit\\ComplianceEngine.ts", "source_location": "L188"}]}